{
  "city": "Nevşehir",
  "region": "İç Anadolu",
  "description": "Peri bacaları ve Kapadokya'nın gizemli coğrafyasında, yeraltı şehirlerinin derinliğini ve bozkırın hüznünü türkülerine katan özgün İç Anadolu kentidir.",
  "themes": ["peri bacaları", "gurbet", "toprak altı gizemliği", "sevda", "yurt sevgisi"],
  "place_names": ["Ürgüp", "Göreme", "Uçhisar", "Avanos", "Ihlara Vadisi", "Kızılırmak"],
  "nature_images": ["peri bacaları", "kırmızı kaya peyzajı", "üzüm bağları", "volkan tufu"],
  "cultural_references": ["Kapadokya yeraltı şehirleri", "güvercin vadisi", "üzüm bağı geleneği", "Nasreddin Hoca"],
  "instruments": {
    "primary": ["bağlama"],
    "secondary": ["kaval", "davul"],
    "avoid": ["kemençe", "tulum"]
  },
  "rhythms": ["serbest uzun hava", "4/4 türkü", "2/4 oyun havası"],
  "tempos": ["yavaş ağıt", "orta tempo türkü", "hareketli oyun havası"],
  "vocal_types": ["erkek solo derin", "kadın solo gizemli"],
  "moods": ["gizemli ve derin", "hüzünlü", "özgün"],
  "lyric_style": {
    "language_notes": "Orta Anadolu ağzı; kaya ve yer altı metaforları, yalın dil",
    "forbidden_styles": ["arabesk", "pop ritmi"],
    "forbidden_words": ["baby", "şampanya"],
    "preferred_forms": ["dörtlük", "koşma"]
  }
}
